aasman/__init__.py
aasman/bounceText.py
aasman/camera.py
aasman/draw_polygon.py
aasman/updateFormAlphaFunc.py
aasman-0.2.1.95.dist-info/licenses/LICENSE
aasman-0.2.1.95.dist-info/METADATA
aasman-0.2.1.95.dist-info/WHEEL
aasman-0.2.1.95.dist-info/top_level.txt
aasman-0.2.1.95.dist-info/RECORD
