Metadata-Version: 2.4
Name: aasman
Version: 0.2.1.95
Summary: A sample Python package for testing
Author-email: Đỉnh Lưu Aasman <luulacdinh.hp2021@gmail.com>
License: MIT
Project-URL: Homepage, https://github.com/LuuLacDinh/aasman
Project-URL: Bug Tracker, https://github.com/LuuLacDinh/aasman
Requires-Python: >=3.7
License-File: LICENSE
Dynamic: license-file
